{"body":"You can consult the [wiki](https://github.com/azrafe7/punk.fx/wiki) to get started with punk.fx or read the \r\nfull package [documentation](http://azrafe7.github.com/punk.fx/docs) to better understand the library's internal classes and methods.\r\nYou can also take a look at this messy [demo](http://dl.dropbox.com/u/32864004/dev/FPDemo/FX%20Project%20PlayTest.swf) to \r\nget an idea of what this all is about. \r\n","google":"","note":"Don't delete this file! It's used internally to help with page regeneration.","name":"punk.fx","tagline":"A library for applying graphic effects in FlashPunk v1.6."}